{
  "generated_at": "2026-03-30 19:43:07.411427",
  "n": 67,
  "alerts": [
    {
      "match_id": "fake-001",
      "home_team": "Juventus",
      "away_team": "Inter",
      "match_date": "2026-03-30",
      "match_time": "14:38",
      "league_id": "Serie A",
      "alerts": [
        {
          "market": "over_15",
          "prob_cal": 0.92,
          "confidence_score": 993.0
        },
        {
          "market": "over_25",
          "prob_cal": 0.65,
          "confidence_score": 847.0
        }
      ]
    },
    {
      "match_id": "fake-002",
      "home_team": "Real Madrid",
      "away_team": "Barcelona",
      "match_date": "2026-03-30",
      "match_time": "14:43",
      "league_id": "La Liga",
      "alerts": [
        {
          "market": "over_15",
          "prob_cal": 0.93,
          "confidence_score": 1178.0
        },
        {
          "market": "over_25",
          "prob_cal": 0.77,
          "confidence_score": 806.0
        }
      ]
    },
    {
      "match_id": "fake-003",
      "home_team": "Bayern Munich",
      "away_team": "Dortmund",
      "match_date": "2026-03-30",
      "match_time": "14:48",
      "league_id": "Bundesliga",
      "alerts": [
        {
          "market": "over_15",
          "prob_cal": 0.89,
          "confidence_score": 976.0
        },
        {
          "market": "over_25",
          "prob_cal": 0.66,
          "confidence_score": 932.0
        }
      ]
    },
    {
      "match_id": "fake-004",
      "home_team": "PSG",
      "away_team": "Lyon",
      "match_date": "2026-03-30",
      "match_time": "14:53",
      "league_id": "Ligue 1",
      "alerts": [
        {
          "market": "over_15",
          "prob_cal": 0.84,
          "confidence_score": 1105.0
        },
        {
          "market": "over_25",
          "prob_cal": 0.69,
          "confidence_score": 943.0
        }
      ]
    },
    {
      "match_id": "fake-005",
      "home_team": "Chelsea",
      "away_team": "Arsenal",
      "match_date": "2026-03-30",
      "match_time": "14:58",
      "league_id": "Premier League",
      "alerts": [
        {
          "market": "over_15",
          "prob_cal": 0.87,
          "confidence_score": 1153.0
        },
        {
          "market": "over_25",
          "prob_cal": 0.76,
          "confidence_score": 782.0
        }
      ]
    },
    {
      "match_id": "fake-006",
      "home_team": "Napoli",
      "away_team": "Milan",
      "match_date": "2026-03-30",
      "match_time": "15:03",
      "league_id": "Serie A",
      "alerts": [
        {
          "market": "over_15",
          "prob_cal": 0.94,
          "confidence_score": 1012.0
        },
        {
          "market": "over_25",
          "prob_cal": 0.78,
          "confidence_score": 827.0
        }
      ]
    },
    {
      "match_id": "fake-007",
      "home_team": "Atletico Madrid",
      "away_team": "Sevilla",
      "match_date": "2026-03-30",
      "match_time": "15:08",
      "league_id": "La Liga",
      "alerts": [
        {
          "market": "over_15",
          "prob_cal": 0.95,
          "confidence_score": 938.0
        },
        {
          "market": "over_25",
          "prob_cal": 0.71,
          "confidence_score": 809.0
        }
      ]
    },
    {
      "match_id": "fake-008",
      "home_team": "Manchester City",
      "away_team": "Liverpool",
      "match_date": "2026-03-30",
      "match_time": "15:13",
      "league_id": "Premier League",
      "alerts": [
        {
          "market": "over_15",
          "prob_cal": 0.94,
          "confidence_score": 1152.0
        },
        {
          "market": "over_25",
          "prob_cal": 0.76,
          "confidence_score": 999.0
        }
      ]
    },
    {
      "match_id": "fake-009",
      "home_team": "Roma",
      "away_team": "Lazio",
      "match_date": "2026-03-30",
      "match_time": "15:18",
      "league_id": "Serie A",
      "alerts": [
        {
          "market": "over_15",
          "prob_cal": 0.9,
          "confidence_score": 1024.0
        },
        {
          "market": "over_25",
          "prob_cal": 0.83,
          "confidence_score": 946.0
        }
      ]
    },
    {
      "match_id": "fake-010",
      "home_team": "Porto",
      "away_team": "Benfica",
      "match_date": "2026-03-30",
      "match_time": "15:23",
      "league_id": "Primeira Liga",
      "alerts": [
        {
          "market": "over_15",
          "prob_cal": 0.94,
          "confidence_score": 1169.0
        },
        {
          "market": "over_25",
          "prob_cal": 0.76,
          "confidence_score": 953.0
        }
      ]
    },
    {
      "match_id": "fake-011",
      "home_team": "Ajax",
      "away_team": "PSV",
      "match_date": "2026-03-30",
      "match_time": "15:28",
      "league_id": "Eredivisie",
      "alerts": [
        {
          "market": "over_15",
          "prob_cal": 0.92,
          "confidence_score": 978.0
        },
        {
          "market": "over_25",
          "prob_cal": 0.66,
          "confidence_score": 867.0
        }
      ]
    },
    {
      "match_id": "fake-012",
      "home_team": "Galatasaray",
      "away_team": "Fenerbahce",
      "match_date": "2026-03-30",
      "match_time": "15:33",
      "league_id": "S\u00fcper Lig",
      "alerts": [
        {
          "market": "over_15",
          "prob_cal": 0.85,
          "confidence_score": 940.0
        },
        {
          "market": "over_25",
          "prob_cal": 0.69,
          "confidence_score": 863.0
        }
      ]
    },
    {
      "match_id": "fake-013",
      "home_team": "Torino",
      "away_team": "Bologna",
      "match_date": "2026-03-30",
      "match_time": "15:38",
      "league_id": "Serie A",
      "alerts": [
        {
          "market": "over_15",
          "prob_cal": 0.92,
          "confidence_score": 1021.0
        },
        {
          "market": "over_25",
          "prob_cal": 0.72,
          "confidence_score": 843.0
        }
      ]
    },
    {
      "match_id": "fake-014",
      "home_team": "West Ham",
      "away_team": "Wolves",
      "match_date": "2026-03-30",
      "match_time": "15:43",
      "league_id": "Premier League",
      "alerts": [
        {
          "market": "over_15",
          "prob_cal": 0.87,
          "confidence_score": 1104.0
        },
        {
          "market": "over_25",
          "prob_cal": 0.82,
          "confidence_score": 963.0
        }
      ]
    },
    {
      "match_id": "fake-015",
      "home_team": "Udinese",
      "away_team": "Empoli",
      "match_date": "2026-03-30",
      "match_time": "15:48",
      "league_id": "Serie A",
      "alerts": [
        {
          "market": "over_15",
          "prob_cal": 0.86,
          "confidence_score": 959.0
        },
        {
          "market": "over_25",
          "prob_cal": 0.78,
          "confidence_score": 894.0
        }
      ]
    },
    {
      "match_id": "fake-016",
      "home_team": "Nice",
      "away_team": "Montpellier",
      "match_date": "2026-03-30",
      "match_time": "15:53",
      "league_id": "Ligue 1",
      "alerts": [
        {
          "market": "over_15",
          "prob_cal": 0.96,
          "confidence_score": 1077.0
        },
        {
          "market": "over_25",
          "prob_cal": 0.77,
          "confidence_score": 985.0
        }
      ]
    },
    {
      "match_id": "fake-017",
      "home_team": "Flamengo",
      "away_team": "Palmeiras",
      "match_date": "2026-03-30",
      "match_time": "15:58",
      "league_id": "Brasileirao",
      "alerts": [
        {
          "market": "over_15",
          "prob_cal": 0.94,
          "confidence_score": 979.0
        },
        {
          "market": "over_25",
          "prob_cal": 0.79,
          "confidence_score": 790.0
        }
      ]
    },
    {
      "match_id": "fake-018",
      "home_team": "Boca Juniors",
      "away_team": "River Plate",
      "match_date": "2026-03-30",
      "match_time": "16:03",
      "league_id": "Primera Division",
      "alerts": [
        {
          "market": "over_15",
          "prob_cal": 0.88,
          "confidence_score": 973.0
        },
        {
          "market": "over_25",
          "prob_cal": 0.7,
          "confidence_score": 1063.0
        }
      ]
    },
    {
      "match_id": "fake-019",
      "home_team": "Santos",
      "away_team": "Gremio",
      "match_date": "2026-03-30",
      "match_time": "16:08",
      "league_id": "Brasileirao",
      "alerts": [
        {
          "market": "over_15",
          "prob_cal": 0.95,
          "confidence_score": 1107.0
        },
        {
          "market": "over_25",
          "prob_cal": 0.71,
          "confidence_score": 899.0
        }
      ]
    },
    {
      "match_id": "fake-020",
      "home_team": "Cruz Azul",
      "away_team": "America",
      "match_date": "2026-03-30",
      "match_time": "16:13",
      "league_id": "Liga MX",
      "alerts": [
        {
          "market": "over_15",
          "prob_cal": 0.95,
          "confidence_score": 989.0
        },
        {
          "market": "over_25",
          "prob_cal": 0.73,
          "confidence_score": 854.0
        }
      ]
    },
    {
      "match_id": "fake-021",
      "home_team": "Sporting CP",
      "away_team": "Braga",
      "match_date": "2026-03-30",
      "match_time": "16:18",
      "league_id": "Primeira Liga",
      "alerts": [
        {
          "market": "over_15",
          "prob_cal": 0.91,
          "confidence_score": 1085.0
        },
        {
          "market": "over_25",
          "prob_cal": 0.7,
          "confidence_score": 1049.0
        }
      ]
    },
    {
      "match_id": "fake-022",
      "home_team": "Strasbourg",
      "away_team": "Lens",
      "match_date": "2026-03-30",
      "match_time": "16:23",
      "league_id": "Ligue 1",
      "alerts": [
        {
          "market": "over_15",
          "prob_cal": 0.89,
          "confidence_score": 1209.0
        },
        {
          "market": "over_25",
          "prob_cal": 0.69,
          "confidence_score": 933.0
        }
      ]
    },
    {
      "match_id": "fake-023",
      "home_team": "Brentford",
      "away_team": "Fulham",
      "match_date": "2026-03-30",
      "match_time": "16:28",
      "league_id": "Premier League",
      "alerts": [
        {
          "market": "over_15",
          "prob_cal": 0.85,
          "confidence_score": 943.0
        },
        {
          "market": "over_25",
          "prob_cal": 0.66,
          "confidence_score": 968.0
        }
      ]
    },
    {
      "match_id": "fake-024",
      "home_team": "Almeria",
      "away_team": "Cadiz",
      "match_date": "2026-03-30",
      "match_time": "16:33",
      "league_id": "La Liga",
      "alerts": [
        {
          "market": "over_15",
          "prob_cal": 0.94,
          "confidence_score": 929.0
        },
        {
          "market": "over_25",
          "prob_cal": 0.73,
          "confidence_score": 894.0
        }
      ]
    },
    {
      "match_id": "fake-025",
      "home_team": "Werder Bremen",
      "away_team": "Augsburg",
      "match_date": "2026-03-30",
      "match_time": "16:38",
      "league_id": "Bundesliga",
      "alerts": [
        {
          "market": "over_15",
          "prob_cal": 0.96,
          "confidence_score": 1201.0
        },
        {
          "market": "over_25",
          "prob_cal": 0.75,
          "confidence_score": 1038.0
        }
      ]
    },
    {
      "match_id": "fake-026",
      "home_team": "Fiorentina",
      "away_team": "Atalanta",
      "match_date": "2026-03-30",
      "match_time": "16:43",
      "league_id": "Serie A",
      "alerts": [
        {
          "market": "over_15",
          "prob_cal": 0.84,
          "confidence_score": 1115.0
        },
        {
          "market": "over_25",
          "prob_cal": 0.78,
          "confidence_score": 941.0
        }
      ]
    },
    {
      "match_id": "fake-027",
      "home_team": "Crystal Palace",
      "away_team": "Ipswich",
      "match_date": "2026-03-30",
      "match_time": "16:48",
      "league_id": "Premier League",
      "alerts": [
        {
          "market": "over_15",
          "prob_cal": 0.87,
          "confidence_score": 943.0
        },
        {
          "market": "over_25",
          "prob_cal": 0.77,
          "confidence_score": 910.0
        }
      ]
    },
    {
      "match_id": "fake-028",
      "home_team": "Lecce",
      "away_team": "Parma",
      "match_date": "2026-03-30",
      "match_time": "16:53",
      "league_id": "Serie A",
      "alerts": [
        {
          "market": "over_15",
          "prob_cal": 0.89,
          "confidence_score": 1173.0
        },
        {
          "market": "over_25",
          "prob_cal": 0.82,
          "confidence_score": 859.0
        }
      ]
    },
    {
      "match_id": "fake-029",
      "home_team": "Marseille",
      "away_team": "Monaco",
      "match_date": "2026-03-30",
      "match_time": "16:58",
      "league_id": "Ligue 1",
      "alerts": [
        {
          "market": "over_15",
          "prob_cal": 0.9,
          "confidence_score": 1184.0
        },
        {
          "market": "over_25",
          "prob_cal": 0.68,
          "confidence_score": 1041.0
        }
      ]
    },
    {
      "match_id": "fake-030",
      "home_team": "Sevilla",
      "away_team": "Real Betis",
      "match_date": "2026-03-30",
      "match_time": "17:03",
      "league_id": "La Liga",
      "alerts": [
        {
          "market": "over_15",
          "prob_cal": 0.88,
          "confidence_score": 1093.0
        },
        {
          "market": "over_25",
          "prob_cal": 0.77,
          "confidence_score": 826.0
        }
      ]
    },
    {
      "match_id": "fake-031",
      "home_team": "Leipzig",
      "away_team": "Hoffenheim",
      "match_date": "2026-03-30",
      "match_time": "17:08",
      "league_id": "Bundesliga",
      "alerts": [
        {
          "market": "over_15",
          "prob_cal": 0.93,
          "confidence_score": 1144.0
        },
        {
          "market": "over_25",
          "prob_cal": 0.75,
          "confidence_score": 939.0
        }
      ]
    },
    {
      "match_id": "fake-032",
      "home_team": "Getafe",
      "away_team": "Leganes",
      "match_date": "2026-03-30",
      "match_time": "17:13",
      "league_id": "La Liga",
      "alerts": [
        {
          "market": "over_15",
          "prob_cal": 0.84,
          "confidence_score": 916.0
        },
        {
          "market": "over_25",
          "prob_cal": 0.71,
          "confidence_score": 1059.0
        }
      ]
    },
    {
      "match_id": "fake-033",
      "home_team": "Atletico MG",
      "away_team": "Internacional",
      "match_date": "2026-03-30",
      "match_time": "17:18",
      "league_id": "Brasileirao",
      "alerts": [
        {
          "market": "over_15",
          "prob_cal": 0.95,
          "confidence_score": 1002.0
        },
        {
          "market": "over_25",
          "prob_cal": 0.8,
          "confidence_score": 797.0
        }
      ]
    },
    {
      "match_id": "fake-034",
      "home_team": "Tigres",
      "away_team": "Monterrey",
      "match_date": "2026-03-30",
      "match_time": "17:23",
      "league_id": "Liga MX",
      "alerts": [
        {
          "market": "over_15",
          "prob_cal": 0.95,
          "confidence_score": 936.0
        },
        {
          "market": "over_25",
          "prob_cal": 0.82,
          "confidence_score": 926.0
        }
      ]
    },
    {
      "match_id": "fake-035",
      "home_team": "Sao Paulo",
      "away_team": "Corinthians",
      "match_date": "2026-03-30",
      "match_time": "17:28",
      "league_id": "Brasileirao",
      "alerts": [
        {
          "market": "over_15",
          "prob_cal": 0.85,
          "confidence_score": 1140.0
        },
        {
          "market": "over_25",
          "prob_cal": 0.79,
          "confidence_score": 819.0
        }
      ]
    },
    {
      "match_id": "fake-036",
      "home_team": "Cagliari",
      "away_team": "Venezia",
      "match_date": "2026-03-30",
      "match_time": "17:33",
      "league_id": "Serie A",
      "alerts": [
        {
          "market": "over_15",
          "prob_cal": 0.9,
          "confidence_score": 990.0
        },
        {
          "market": "over_25",
          "prob_cal": 0.75,
          "confidence_score": 1042.0
        }
      ]
    },
    {
      "match_id": "fake-037",
      "home_team": "Newcastle",
      "away_team": "Aston Villa",
      "match_date": "2026-03-30",
      "match_time": "17:38",
      "league_id": "Premier League",
      "alerts": [
        {
          "market": "over_15",
          "prob_cal": 0.89,
          "confidence_score": 1072.0
        },
        {
          "market": "over_25",
          "prob_cal": 0.69,
          "confidence_score": 999.0
        }
      ]
    },
    {
      "match_id": "fake-038",
      "home_team": "Girona",
      "away_team": "Rayo Vallecano",
      "match_date": "2026-03-30",
      "match_time": "17:43",
      "league_id": "La Liga",
      "alerts": [
        {
          "market": "over_15",
          "prob_cal": 0.86,
          "confidence_score": 1209.0
        },
        {
          "market": "over_25",
          "prob_cal": 0.71,
          "confidence_score": 975.0
        }
      ]
    },
    {
      "match_id": "fake-039",
      "home_team": "Eintracht",
      "away_team": "Freiburg",
      "match_date": "2026-03-30",
      "match_time": "17:48",
      "league_id": "Bundesliga",
      "alerts": [
        {
          "market": "over_15",
          "prob_cal": 0.89,
          "confidence_score": 946.0
        },
        {
          "market": "over_25",
          "prob_cal": 0.74,
          "confidence_score": 847.0
        }
      ]
    },
    {
      "match_id": "fake-040",
      "home_team": "Le Havre",
      "away_team": "Angers",
      "match_date": "2026-03-30",
      "match_time": "17:53",
      "league_id": "Ligue 1",
      "alerts": [
        {
          "market": "over_15",
          "prob_cal": 0.88,
          "confidence_score": 979.0
        },
        {
          "market": "over_25",
          "prob_cal": 0.76,
          "confidence_score": 846.0
        }
      ]
    },
    {
      "match_id": "fake-041",
      "home_team": "Empoli",
      "away_team": "Verona",
      "match_date": "2026-03-30",
      "match_time": "17:58",
      "league_id": "Serie A",
      "alerts": [
        {
          "market": "over_15",
          "prob_cal": 0.85,
          "confidence_score": 979.0
        },
        {
          "market": "over_25",
          "prob_cal": 0.76,
          "confidence_score": 1052.0
        }
      ]
    },
    {
      "match_id": "fake-042",
      "home_team": "Las Palmas",
      "away_team": "Espanyol",
      "match_date": "2026-03-30",
      "match_time": "18:03",
      "league_id": "La Liga",
      "alerts": [
        {
          "market": "over_15",
          "prob_cal": 0.94,
          "confidence_score": 981.0
        },
        {
          "market": "over_25",
          "prob_cal": 0.66,
          "confidence_score": 981.0
        }
      ]
    },
    {
      "match_id": "fake-043",
      "home_team": "Juventus",
      "away_team": "Inter",
      "match_date": "2026-03-30",
      "match_time": "18:08",
      "league_id": "Serie A",
      "alerts": [
        {
          "market": "over_15",
          "prob_cal": 0.87,
          "confidence_score": 1191.0
        },
        {
          "market": "over_25",
          "prob_cal": 0.67,
          "confidence_score": 951.0
        }
      ]
    },
    {
      "match_id": "fake-044",
      "home_team": "Real Madrid",
      "away_team": "Barcelona",
      "match_date": "2026-03-30",
      "match_time": "18:13",
      "league_id": "La Liga",
      "alerts": [
        {
          "market": "over_15",
          "prob_cal": 0.9,
          "confidence_score": 1152.0
        },
        {
          "market": "over_25",
          "prob_cal": 0.79,
          "confidence_score": 837.0
        }
      ]
    },
    {
      "match_id": "fake-045",
      "home_team": "Bayern Munich",
      "away_team": "Dortmund",
      "match_date": "2026-03-30",
      "match_time": "18:18",
      "league_id": "Bundesliga",
      "alerts": [
        {
          "market": "over_15",
          "prob_cal": 0.85,
          "confidence_score": 1037.0
        },
        {
          "market": "over_25",
          "prob_cal": 0.73,
          "confidence_score": 920.0
        }
      ]
    },
    {
      "match_id": "fake-046",
      "home_team": "PSG",
      "away_team": "Lyon",
      "match_date": "2026-03-30",
      "match_time": "18:23",
      "league_id": "Ligue 1",
      "alerts": [
        {
          "market": "over_15",
          "prob_cal": 0.93,
          "confidence_score": 1205.0
        },
        {
          "market": "over_25",
          "prob_cal": 0.77,
          "confidence_score": 810.0
        }
      ]
    },
    {
      "match_id": "fake-047",
      "home_team": "Chelsea",
      "away_team": "Arsenal",
      "match_date": "2026-03-30",
      "match_time": "18:28",
      "league_id": "Premier League",
      "alerts": [
        {
          "market": "over_15",
          "prob_cal": 0.89,
          "confidence_score": 1169.0
        },
        {
          "market": "over_25",
          "prob_cal": 0.71,
          "confidence_score": 855.0
        }
      ]
    },
    {
      "match_id": "fake-048",
      "home_team": "Napoli",
      "away_team": "Milan",
      "match_date": "2026-03-30",
      "match_time": "18:33",
      "league_id": "Serie A",
      "alerts": [
        {
          "market": "over_15",
          "prob_cal": 0.86,
          "confidence_score": 1037.0
        },
        {
          "market": "over_25",
          "prob_cal": 0.73,
          "confidence_score": 864.0
        }
      ]
    },
    {
      "match_id": "fake-049",
      "home_team": "Atletico Madrid",
      "away_team": "Sevilla",
      "match_date": "2026-03-30",
      "match_time": "18:38",
      "league_id": "La Liga",
      "alerts": [
        {
          "market": "over_15",
          "prob_cal": 0.87,
          "confidence_score": 1043.0
        },
        {
          "market": "over_25",
          "prob_cal": 0.82,
          "confidence_score": 1038.0
        }
      ]
    },
    {
      "match_id": "fake-050",
      "home_team": "Manchester City",
      "away_team": "Liverpool",
      "match_date": "2026-03-30",
      "match_time": "18:43",
      "league_id": "Premier League",
      "alerts": [
        {
          "market": "over_15",
          "prob_cal": 0.91,
          "confidence_score": 1210.0
        },
        {
          "market": "over_25",
          "prob_cal": 0.66,
          "confidence_score": 1031.0
        }
      ]
    },
    {
      "match_id": "fake-051",
      "home_team": "Roma",
      "away_team": "Lazio",
      "match_date": "2026-03-30",
      "match_time": "18:48",
      "league_id": "Serie A",
      "alerts": [
        {
          "market": "over_15",
          "prob_cal": 0.96,
          "confidence_score": 1165.0
        },
        {
          "market": "over_25",
          "prob_cal": 0.82,
          "confidence_score": 830.0
        }
      ]
    },
    {
      "match_id": "fake-052",
      "home_team": "Porto",
      "away_team": "Benfica",
      "match_date": "2026-03-30",
      "match_time": "18:53",
      "league_id": "Primeira Liga",
      "alerts": [
        {
          "market": "over_15",
          "prob_cal": 0.9,
          "confidence_score": 1030.0
        },
        {
          "market": "over_25",
          "prob_cal": 0.69,
          "confidence_score": 798.0
        }
      ]
    },
    {
      "match_id": "fake-053",
      "home_team": "Ajax",
      "away_team": "PSV",
      "match_date": "2026-03-30",
      "match_time": "18:58",
      "league_id": "Eredivisie",
      "alerts": [
        {
          "market": "over_15",
          "prob_cal": 0.89,
          "confidence_score": 990.0
        },
        {
          "market": "over_25",
          "prob_cal": 0.83,
          "confidence_score": 1015.0
        }
      ]
    },
    {
      "match_id": "fake-054",
      "home_team": "Galatasaray",
      "away_team": "Fenerbahce",
      "match_date": "2026-03-30",
      "match_time": "19:03",
      "league_id": "S\u00fcper Lig",
      "alerts": [
        {
          "market": "over_15",
          "prob_cal": 0.89,
          "confidence_score": 1197.0
        },
        {
          "market": "over_25",
          "prob_cal": 0.73,
          "confidence_score": 1079.0
        }
      ]
    },
    {
      "match_id": "fake-055",
      "home_team": "Torino",
      "away_team": "Bologna",
      "match_date": "2026-03-30",
      "match_time": "19:08",
      "league_id": "Serie A",
      "alerts": [
        {
          "market": "over_15",
          "prob_cal": 0.91,
          "confidence_score": 956.0
        },
        {
          "market": "over_25",
          "prob_cal": 0.78,
          "confidence_score": 869.0
        }
      ]
    },
    {
      "match_id": "fake-056",
      "home_team": "West Ham",
      "away_team": "Wolves",
      "match_date": "2026-03-30",
      "match_time": "19:13",
      "league_id": "Premier League",
      "alerts": [
        {
          "market": "over_15",
          "prob_cal": 0.96,
          "confidence_score": 1073.0
        },
        {
          "market": "over_25",
          "prob_cal": 0.75,
          "confidence_score": 1004.0
        }
      ]
    },
    {
      "match_id": "fake-057",
      "home_team": "Udinese",
      "away_team": "Empoli",
      "match_date": "2026-03-30",
      "match_time": "19:18",
      "league_id": "Serie A",
      "alerts": [
        {
          "market": "over_15",
          "prob_cal": 0.85,
          "confidence_score": 1061.0
        },
        {
          "market": "over_25",
          "prob_cal": 0.76,
          "confidence_score": 1036.0
        }
      ]
    },
    {
      "match_id": "fake-058",
      "home_team": "Nice",
      "away_team": "Montpellier",
      "match_date": "2026-03-30",
      "match_time": "19:23",
      "league_id": "Ligue 1",
      "alerts": [
        {
          "market": "over_15",
          "prob_cal": 0.86,
          "confidence_score": 934.0
        },
        {
          "market": "over_25",
          "prob_cal": 0.82,
          "confidence_score": 836.0
        }
      ]
    },
    {
      "match_id": "fake-059",
      "home_team": "Flamengo",
      "away_team": "Palmeiras",
      "match_date": "2026-03-30",
      "match_time": "19:28",
      "league_id": "Brasileirao",
      "alerts": [
        {
          "market": "over_15",
          "prob_cal": 0.91,
          "confidence_score": 981.0
        },
        {
          "market": "over_25",
          "prob_cal": 0.77,
          "confidence_score": 816.0
        }
      ]
    },
    {
      "match_id": "fake-060",
      "home_team": "Boca Juniors",
      "away_team": "River Plate",
      "match_date": "2026-03-30",
      "match_time": "19:33",
      "league_id": "Primera Division",
      "alerts": [
        {
          "market": "over_15",
          "prob_cal": 0.95,
          "confidence_score": 1088.0
        },
        {
          "market": "over_25",
          "prob_cal": 0.69,
          "confidence_score": 966.0
        }
      ]
    },
    {
      "match_id": "fake-061",
      "home_team": "Santos",
      "away_team": "Gremio",
      "match_date": "2026-03-30",
      "match_time": "19:38",
      "league_id": "Brasileirao",
      "alerts": [
        {
          "market": "over_15",
          "prob_cal": 0.89,
          "confidence_score": 1067.0
        },
        {
          "market": "over_25",
          "prob_cal": 0.76,
          "confidence_score": 1060.0
        }
      ]
    },
    {
      "match_id": "fake-062",
      "home_team": "Cruz Azul",
      "away_team": "America",
      "match_date": "2026-03-30",
      "match_time": "19:43",
      "league_id": "Liga MX",
      "alerts": [
        {
          "market": "over_15",
          "prob_cal": 0.86,
          "confidence_score": 982.0
        },
        {
          "market": "over_25",
          "prob_cal": 0.78,
          "confidence_score": 899.0
        }
      ]
    },
    {
      "match_id": "fake-063",
      "home_team": "Sporting CP",
      "away_team": "Braga",
      "match_date": "2026-03-30",
      "match_time": "19:48",
      "league_id": "Primeira Liga",
      "alerts": [
        {
          "market": "over_15",
          "prob_cal": 0.92,
          "confidence_score": 1005.0
        },
        {
          "market": "over_25",
          "prob_cal": 0.7,
          "confidence_score": 1006.0
        }
      ]
    },
    {
      "match_id": "fake-064",
      "home_team": "Strasbourg",
      "away_team": "Lens",
      "match_date": "2026-03-30",
      "match_time": "19:53",
      "league_id": "Ligue 1",
      "alerts": [
        {
          "market": "over_15",
          "prob_cal": 0.85,
          "confidence_score": 1210.0
        },
        {
          "market": "over_25",
          "prob_cal": 0.73,
          "confidence_score": 1079.0
        }
      ]
    },
    {
      "match_id": "fake-065",
      "home_team": "Brentford",
      "away_team": "Fulham",
      "match_date": "2026-03-30",
      "match_time": "19:58",
      "league_id": "Premier League",
      "alerts": [
        {
          "market": "over_15",
          "prob_cal": 0.85,
          "confidence_score": 990.0
        },
        {
          "market": "over_25",
          "prob_cal": 0.69,
          "confidence_score": 1060.0
        }
      ]
    },
    {
      "match_id": "fake-066",
      "home_team": "Almeria",
      "away_team": "Cadiz",
      "match_date": "2026-03-30",
      "match_time": "20:03",
      "league_id": "La Liga",
      "alerts": [
        {
          "market": "over_15",
          "prob_cal": 0.95,
          "confidence_score": 1021.0
        },
        {
          "market": "over_25",
          "prob_cal": 0.81,
          "confidence_score": 827.0
        }
      ]
    },
    {
      "match_id": "fake-067",
      "home_team": "Werder Bremen",
      "away_team": "Augsburg",
      "match_date": "2026-03-30",
      "match_time": "20:08",
      "league_id": "Bundesliga",
      "alerts": [
        {
          "market": "over_15",
          "prob_cal": 0.94,
          "confidence_score": 1094.0
        },
        {
          "market": "over_25",
          "prob_cal": 0.78,
          "confidence_score": 1076.0
        }
      ]
    }
  ]
}